{"format":2,"version":"5.2.1","globals":"c3fc29d529a3af98c1a2065daa2addf6","files":{"src_auth_py":{"hash":"b32915f848afef8f370a3b66d3f2827b","index":{"nums":[1,54,0,45,0,0,0],"html_filename":"src_auth_py.html","relative_filename":"src\\auth.py"}},"src_auth_test_py":{"hash":"1fa323888ab04feaf645af283275dfe3","index":{"nums":[1,35,0,25,0,0,0],"html_filename":"src_auth_test_py.html","relative_filename":"src\\auth_test.py"}},"src_data_py":{"hash":"12a85dee3c9793ed2bcb140e2bb2cede","index":{"nums":[1,28,0,18,0,0,0],"html_filename":"src_data_py.html","relative_filename":"src\\data.py"}},"src_error_py":{"hash":"3f8f50978faaae2e594c1383884988b1","index":{"nums":[1,4,0,0,0,0,0],"html_filename":"src_error_py.html","relative_filename":"src\\error.py"}},"src_other_py":{"hash":"5e710770c85e95a2fa2abb47a59ea31e","index":{"nums":[1,9,0,5,0,0,0],"html_filename":"src_other_py.html","relative_filename":"src\\other.py"}}}}